flwr_attacks/__init__.py
flwr_attacks/aggregation_tailored.py
flwr_attacks/algorithms.py
flwr_attacks/attack.py
flwr_attacks/computations.py
flwr_attacks/helpers/__init__.py
flwr_attacks/helpers/debug_matrix.py
flwr_attacks/history.py
flwr_attacks/lie.py
flwr_attacks/minmax.py
flwr_attacks/minsum.py
flwr_attacks/model_poisoning.py
flwr_attacks/optimizers.py
flwr_attacks/pga.py
flwr_attacks/server.py
flwr_attacks/simple_agrs.py
flwr_attacks/utils.py
flwr_attacks-0.1.4.dist-info/LICENCE
flwr_attacks-0.1.4.dist-info/METADATA
flwr_attacks-0.1.4.dist-info/WHEEL
flwr_attacks-0.1.4.dist-info/RECORD
