Metadata-Version: 2.1
Name: flwr_attacks
Version: 0.1.4
Summary: Flower Attacks: This is an extension of the Flower framework for Federated Learning. It provides an extenion module that allows the user to perform various attacks on the federated learning process.
Home-page: https://github.com/n45os/flwr_attacks
Keywords: federated learning,flower,attacks,adversarial attacks,machine learning,privacy
Author: Nassos Bountioukos Spinaris
Author-email: nassosbountioukos@gmail.com
Requires-Python: >=3.8
Classifier: Development Status :: 3 - Alpha
Classifier: Intended Audience :: Developers
Classifier: License :: OSI Approved :: Apache Software License
Classifier: Operating System :: MacOS :: MacOS X
Classifier: Operating System :: POSIX :: Linux
Classifier: Programming Language :: Python :: 3
Classifier: Programming Language :: Python :: 3.8
Classifier: Programming Language :: Python :: 3.9
Classifier: Programming Language :: Python :: 3.10
Classifier: Programming Language :: Python :: 3.11
Classifier: Programming Language :: Python :: 3.12
Classifier: Topic :: Scientific/Engineering :: Artificial Intelligence
Classifier: Topic :: Scientific/Engineering :: Information Analysis
Classifier: Topic :: Security
Classifier: Topic :: Software Development :: Libraries
Classifier: Topic :: Software Development :: Libraries :: Python Modules
Classifier: Typing :: Typed
Requires-Dist: flwr (>=1.6.0)
Project-URL: Repository, https://github.com/n45os/flwr_attacks
